{"4": [{"feature": "n_circles", "zscore": -1.779}, {"feature": "horizontal_symmetry", "zscore": 1.362}, {"feature": "n_lines", "zscore": -1.278}, {"feature": "connected_components", "zscore": -1.227}, {"feature": "endpoints", "zscore": -1.131}, {"feature": "vertical_symmetry", "zscore": -0.612}, {"feature": "compactness", "zscore": 0.46}, {"feature": "aspect_ratio", "zscore": -0.422}, {"feature": "fractal_dimension", "zscore": -0.418}, {"feature": "holes", "zscore": 0.196}, {"feature": "ink_ratio", "zscore": -0.161}, {"feature": "junctions", "zscore": 0.109}], "7": [{"feature": "connected_components", "zscore": -0.667}, {"feature": "endpoints", "zscore": -0.559}, {"feature": "compactness", "zscore": 0.443}, {"feature": "aspect_ratio", "zscore": -0.382}, {"feature": "fractal_dimension", "zscore": 0.364}, {"feature": "n_circles", "zscore": -0.341}, {"feature": "horizontal_symmetry", "zscore": 0.337}, {"feature": "ink_ratio", "zscore": 0.323}, {"feature": "n_lines", "zscore": -0.285}, {"feature": "junctions", "zscore": 0.104}, {"feature": "holes", "zscore": 0.085}, {"feature": "vertical_symmetry", "zscore": -0.002}], "2": [{"feature": "ink_ratio", "zscore": -0.598}, {"feature": "compactness", "zscore": -0.568}, {"feature": "holes", "zscore": -0.532}, {"feature": "junctions", "zscore": -0.505}, {"feature": "n_lines", "zscore": -0.495}, {"feature": "fractal_dimension", "zscore": -0.383}, {"feature": "aspect_ratio", "zscore": -0.343}, {"feature": "vertical_symmetry", "zscore": -0.254}, {"feature": "n_circles", "zscore": -0.2}, {"feature": "connected_components", "zscore": 0.141}, {"feature": "endpoints", "zscore": -0.036}, {"feature": "horizontal_symmetry", "zscore": -0.022}], "5": [{"feature": "fractal_dimension", "zscore": 0.663}, {"feature": "vertical_symmetry", "zscore": 0.653}, {"feature": "ink_ratio", "zscore": 0.634}, {"feature": "compactness", "zscore": 0.591}, {"feature": "junctions", "zscore": 0.517}, {"feature": "n_lines", "zscore": 0.371}, {"feature": "endpoints", "zscore": 0.343}, {"feature": "aspect_ratio", "zscore": 0.286}, {"feature": "n_circles", "zscore": 0.215}, {"feature": "horizontal_symmetry", "zscore": 0.202}, {"feature": "holes", "zscore": -0.041}, {"feature": "connected_components", "zscore": 0.014}], "3": [{"feature": "holes", "zscore": 2.358}, {"feature": "ink_ratio", "zscore": 1.924}, {"feature": "compactness", "zscore": 1.591}, {"feature": "junctions", "zscore": 1.553}, {"feature": "fractal_dimension", "zscore": 1.328}, {"feature": "n_lines", "zscore": 1.308}, {"feature": "n_circles", "zscore": 0.841}, {"feature": "vertical_symmetry", "zscore": 0.637}, {"feature": "connected_components", "zscore": -0.602}, {"feature": "endpoints", "zscore": -0.282}, {"feature": "aspect_ratio", "zscore": 0.25}, {"feature": "horizontal_symmetry", "zscore": 0.048}], "1": [{"feature": "fractal_dimension", "zscore": -1.665}, {"feature": "compactness", "zscore": -1.566}, {"feature": "ink_ratio", "zscore": -1.47}, {"feature": "connected_components", "zscore": 1.196}, {"feature": "junctions", "zscore": -1.056}, {"feature": "horizontal_symmetry", "zscore": -0.901}, {"feature": "vertical_symmetry", "zscore": -0.736}, {"feature": "endpoints", "zscore": 0.581}, {"feature": "holes", "zscore": -0.571}, {"feature": "n_circles", "zscore": 0.455}, {"feature": "aspect_ratio", "zscore": -0.413}, {"feature": "n_lines", "zscore": 0.146}], "8": [{"feature": "aspect_ratio", "zscore": 6.006}, {"feature": "n_lines", "zscore": 4.897}, {"feature": "n_circles", "zscore": 4.438}, {"feature": "junctions", "zscore": 4.168}, {"feature": "endpoints", "zscore": 4.093}, {"feature": "holes", "zscore": 3.508}, {"feature": "connected_components", "zscore": 2.52}, {"feature": "vertical_symmetry", "zscore": -0.857}, {"feature": "horizontal_symmetry", "zscore": -0.504}, {"feature": "fractal_dimension", "zscore": 0.446}, {"feature": "compactness", "zscore": -0.303}, {"feature": "ink_ratio", "zscore": 0.208}], "6": [{"feature": "aspect_ratio", "zscore": 2.114}, {"feature": "n_circles", "zscore": -1.17}, {"feature": "junctions", "zscore": -0.635}, {"feature": "holes", "zscore": -0.633}, {"feature": "horizontal_symmetry", "zscore": -0.6}, {"feature": "n_lines", "zscore": -0.506}, {"feature": "compactness", "zscore": 0.498}, {"feature": "vertical_symmetry", "zscore": 0.449}, {"feature": "ink_ratio", "zscore": 0.407}, {"feature": "fractal_dimension", "zscore": 0.365}, {"feature": "endpoints", "zscore": -0.335}, {"feature": "connected_components", "zscore": -0.167}]}